{
  "UserAgent": "MobileHub/1.0",
  "Version": "1.0",
  "CredentialsProvider": {
    "CognitoIdentity": {
      "Default": {
        "PoolId": "us-east-1:a87a7af8-7f96-499e-89d1-ecf8d432d341",
        "Region": "us-east-1"
      }
    }
  },
  "IdentityManager": {
    "Default": {}
  },
  "PinpointAnalytics": {
    "Default": {
      "AppId": "b718f50d7212427f9bc09885f58864b9",
      "Region": "us-east-1"
    }
  },
  "PinpointTargeting": {
    "Default": {
      "Region": "us-east-1"
    }
  }
}